cdown/__init__.py
cdown/__main__.py
cdown/cli.py
cdown/core.py
cdown/exceptions.py
cdown-0.1.0.dist-info/entry_points.txt
cdown-0.1.0.dist-info/LICENSE
cdown-0.1.0.dist-info/WHEEL
cdown-0.1.0.dist-info/METADATA
cdown-0.1.0.dist-info/RECORD
