Metadata-Version: 2.1
Name: cdown
Version: 0.1.0
Summary: Tools for CODEOWNERS files
Home-page: https://github.com/andreoliwa/python-cdown
License: MIT
Author: W Augusto Andreoli
Author-email: andreoliwa@gmail.com
Requires-Python: >=3.7,<4.0
Classifier: Development Status :: 3 - Alpha
Classifier: Intended Audience :: Developers
Classifier: License :: OSI Approved :: MIT License
Classifier: Operating System :: POSIX
Classifier: Operating System :: Unix
Classifier: Programming Language :: Python
Classifier: Programming Language :: Python :: 3
Classifier: Programming Language :: Python :: 3.7
Classifier: Programming Language :: Python :: 3.8
Classifier: Programming Language :: Python :: 3.9
Classifier: Topic :: Utilities
Provides-Extra: docs
Requires-Dist: click
Requires-Dist: gitignore_parser
Requires-Dist: sphinx (>=1.3); extra == "docs"
Requires-Dist: sphinx-rtd-theme; extra == "docs"
Project-URL: Changelog, https://python-cdown.readthedocs.io/en/latest/changelog.html
Project-URL: Documentation, https://python-cdown.readthedocs.io/
Project-URL: Issue Tracker, https://github.com/andreoliwa/python-cdown/issues
Project-URL: Repository, https://github.com/andreoliwa/python-cdown
